setup.cfg
setup.py
gh_quick_release/Errors.py
gh_quick_release/GhClient.py
gh_quick_release/GitClient.py
gh_quick_release/__init__.py
gh_quick_release.egg-info/PKG-INFO
gh_quick_release.egg-info/SOURCES.txt
gh_quick_release.egg-info/dependency_links.txt
gh_quick_release.egg-info/entry_points.txt
gh_quick_release.egg-info/requires.txt
gh_quick_release.egg-info/top_level.txt