Metadata-Version: 1.0
Name: gh-quick-release
Version: 0.9
Summary: Create a new release quickly
Home-page: https://github.com/AGhost-7/gh-quick-release
Author: Jonathan Boudreau
Author-email: jonathan.boudreau.92@gmail.com
License: UNKNOWN
Keywords: release,npm,github,nodejs
Platform: UNKNOWN
